odoo/addons/stock_picking_origin_reference_purchase/README.rst
odoo/addons/stock_picking_origin_reference_purchase/__init__.py
odoo/addons/stock_picking_origin_reference_purchase/__manifest__.py
odoo/addons/stock_picking_origin_reference_purchase/i18n/stock_picking_origin_reference_purchase.pot
odoo/addons/stock_picking_origin_reference_purchase/models/__init__.py
odoo/addons/stock_picking_origin_reference_purchase/models/stock_picking.py
odoo/addons/stock_picking_origin_reference_purchase/readme/CONTRIBUTORS.rst
odoo/addons/stock_picking_origin_reference_purchase/readme/DESCRIPTION.rst
odoo/addons/stock_picking_origin_reference_purchase/static/description/icon.png
odoo/addons/stock_picking_origin_reference_purchase/static/description/index.html
odoo/addons/stock_picking_origin_reference_purchase/tests/__init__.py
odoo/addons/stock_picking_origin_reference_purchase/tests/test_stock_picking_origin_reference_purchase.py
odoo13_addon_stock_picking_origin_reference_purchase-13.0.1.0.1.dev4.dist-info/METADATA
odoo13_addon_stock_picking_origin_reference_purchase-13.0.1.0.1.dev4.dist-info/WHEEL
odoo13_addon_stock_picking_origin_reference_purchase-13.0.1.0.1.dev4.dist-info/top_level.txt
odoo13_addon_stock_picking_origin_reference_purchase-13.0.1.0.1.dev4.dist-info/RECORD
